aiob2/__init__.py
aiob2/bucket.py
aiob2/errors.py
aiob2/file.py
aiob2/http.py
aiob2/models/__init__.py
aiob2/models/account.py
aiob2/models/archetypes.py
aiob2/models/bucket.py
aiob2/models/file.py
aiob2/py.typed
aiob2/utils.py
aiob2-0.9.1.dist-info/LICENSE
aiob2-0.9.1.dist-info/METADATA
aiob2-0.9.1.dist-info/WHEEL
aiob2-0.9.1.dist-info/RECORD
