Metadata-Version: 2.1
Name: aiob2
Version: 0.9.1
Summary: A simple and easy to use async wrapper for Backblaze's B2 bucket API.
Home-page: https://github.com/Void-ux/aiob2
License: MIT
Keywords: backblaze,b2,cloud,storage
Author: Dan
Author-email: the.void.altacc@gmail.com
Requires-Python: >=3.8,<4.0
Classifier: Intended Audience :: Developers
Classifier: License :: OSI Approved :: MIT License
Classifier: Natural Language :: English
Classifier: Operating System :: OS Independent
Classifier: Programming Language :: Python :: 3
Classifier: Programming Language :: Python :: 3.8
Classifier: Programming Language :: Python :: 3.9
Classifier: Programming Language :: Python :: 3.10
Classifier: Programming Language :: Python :: 3.11
Classifier: Programming Language :: Python :: 3.12
Classifier: Programming Language :: Python :: 3.13
Provides-Extra: speed
Requires-Dist: aiofiles (>=24.1.0,<25.0.0)
Requires-Dist: aiohttp (>=3.8.1,<4.0.0)
Requires-Dist: typing-extensions (>=4.4.0,<5.0.0)
Project-URL: Bug Tracker, https://github.com/Void-ux/aiob2/issues/
Project-URL: Documentation, https://aiob2.readthedocs.io/en/latest/
Project-URL: Repository, https://github.com/Void-ux/aiob2
